setup.py
datazilla.egg-info/PKG-INFO
datazilla.egg-info/SOURCES.txt
datazilla.egg-info/dependency_links.txt
datazilla.egg-info/not-zip-safe
datazilla.egg-info/requires.txt
datazilla.egg-info/top_level.txt
dzclient/__init__.py
dzclient/client.py