Metadata-Version: 1.0
Name: datazilla
Version: 1.4
Summary: Python library to interact with the datazilla server
Home-page: https://github.com/mozilla/datazilla_client
Author: Malini Das
Author-email: mdas@mozilla.com
License: MPL
Platform: UNKNOWN
